thrift_tools/__init__.py
thrift_tools/file_reader.py
thrift_tools/idl.py
thrift_tools/message_sniffer.py
thrift_tools/printer.py
thrift_tools/sniffer.py
thrift_tools/stats.py
thrift_tools/stream_handler.py
thrift_tools/thrift_diff.py
thrift_tools/thrift_file.py
thrift_tools/thrift_message.py
thrift_tools/thrift_struct.py
thrift_tools/tool.py
thrift_tools/util.py
thrift_tools/tests/__init__.py
thrift_tools/tests/test_basic.py
thrift_tools/tests/test_diff.py
thrift_tools/tests/test_file_reader.py
thrift_tools/tests/test_idl.py
thrift_tools/tests/test_printer.py
thrift_tools/tests/test_struct.py
thrift_tools/tests/util.py
thrift_tools-0.0.7.data/scripts/thrift-file-reader
thrift_tools-0.0.7.data/scripts/thrift-tool
thrift_tools-0.0.7.dist-info/LICENSE
thrift_tools-0.0.7.dist-info/METADATA
thrift_tools-0.0.7.dist-info/WHEEL
thrift_tools-0.0.7.dist-info/top_level.txt
thrift_tools-0.0.7.dist-info/RECORD
