Metadata-Version: 2.1
Name: thrift-tools
Version: 0.0.7
Summary: Thrift protocol analyzer
Home-page: https://github.com/pinterest/thrift-tools
Author: Raul Gutierrez Segales
Author-email: rgs@pinterest.com
License: Apache
Keywords: thrift pcap
Platform: UNKNOWN
Classifier: Development Status :: 3 - Alpha
Classifier: License :: OSI Approved :: Apache Software License
Classifier: Programming Language :: Python :: 2.7
Classifier: Programming Language :: Python :: 3.5
Classifier: Programming Language :: Python :: 3.6
Classifier: Programming Language :: Python :: 3.7
Classifier: Topic :: System :: Distributed Computing
Classifier: Topic :: System :: Networking
Requires-Dist: ansicolors
Requires-Dist: dpkt (==1.9.2)
Requires-Dist: ptsd (==0.2.0)
Requires-Dist: scapy (==2.4.5)
Requires-Dist: thrift (==0.11.0)
Requires-Dist: tabulate
Provides-Extra: test
Requires-Dist: ansicolors ; extra == 'test'
Requires-Dist: dpkt ; extra == 'test'
Requires-Dist: nose ; extra == 'test'
Requires-Dist: ptsd (==0.2.0) ; extra == 'test'
Requires-Dist: scapy (==2.4.5) ; extra == 'test'
Requires-Dist: six (==1.12.0) ; extra == 'test'
Requires-Dist: thrift (==0.11.0) ; extra == 'test'
Requires-Dist: tabulate ; extra == 'test'
